aliyunsdkhitsdb/__init__.py
aliyunsdkhitsdb/endpoint.py
aliyunsdkhitsdb/request/__init__.py
aliyunsdkhitsdb/request/v20200615/CreateLdpsComputeGroupRequest.py
aliyunsdkhitsdb/request/v20200615/CreateLdpsNamespaceRequest.py
aliyunsdkhitsdb/request/v20200615/CreateLindormInstanceRequest.py
aliyunsdkhitsdb/request/v20200615/DeleteLdpsComputeGroupRequest.py
aliyunsdkhitsdb/request/v20200615/DescribeRegionsRequest.py
aliyunsdkhitsdb/request/v20200615/GetEngineDefaultAuthRequest.py
aliyunsdkhitsdb/request/v20200615/GetInstanceIpWhiteListRequest.py
aliyunsdkhitsdb/request/v20200615/GetInstanceSecurityGroupsRequest.py
aliyunsdkhitsdb/request/v20200615/GetLdpsComputeGroupRequest.py
aliyunsdkhitsdb/request/v20200615/GetLdpsNamespacedQuotaRequest.py
aliyunsdkhitsdb/request/v20200615/GetLdpsResourceCostRequest.py
aliyunsdkhitsdb/request/v20200615/GetLindormInstanceEngineListRequest.py
aliyunsdkhitsdb/request/v20200615/GetLindormInstanceListRequest.py
aliyunsdkhitsdb/request/v20200615/GetLindormInstanceRequest.py
aliyunsdkhitsdb/request/v20200615/ListLdpsComputeGroupsRequest.py
aliyunsdkhitsdb/request/v20200615/ListTagResourcesRequest.py
aliyunsdkhitsdb/request/v20200615/ModifyInstancePayTypeRequest.py
aliyunsdkhitsdb/request/v20200615/ReleaseLindormInstanceRequest.py
aliyunsdkhitsdb/request/v20200615/RenewLindormInstanceRequest.py
aliyunsdkhitsdb/request/v20200615/RestartLdpsComputeGroupRequest.py
aliyunsdkhitsdb/request/v20200615/SwitchLSQLV3MySQLServiceRequest.py
aliyunsdkhitsdb/request/v20200615/TagResourcesRequest.py
aliyunsdkhitsdb/request/v20200615/UntagResourcesRequest.py
aliyunsdkhitsdb/request/v20200615/UpdateInstanceIpWhiteListRequest.py
aliyunsdkhitsdb/request/v20200615/UpdateInstanceSecurityGroupsRequest.py
aliyunsdkhitsdb/request/v20200615/UpdateLdpsComputeGroupRequest.py
aliyunsdkhitsdb/request/v20200615/UpgradeLindormInstanceRequest.py
aliyunsdkhitsdb/request/v20200615/__init__.py
aliyun_python_sdk_hitsdb-3.1.15.dist-info/LICENSE
aliyun_python_sdk_hitsdb-3.1.15.dist-info/METADATA
aliyun_python_sdk_hitsdb-3.1.15.dist-info/WHEEL
aliyun_python_sdk_hitsdb-3.1.15.dist-info/top_level.txt
aliyun_python_sdk_hitsdb-3.1.15.dist-info/RECORD
